marcel/__init__.py
marcel/api.py
marcel/argsparser.py
marcel/argsvalidator.py
marcel/builtin.py
marcel/builtins.py
marcel/cliargs.py
marcel/compilable.py
marcel/configscript.py
marcel/core.py
marcel/directorystate.py
marcel/env.py
marcel/envvalue.py
marcel/exception.py
marcel/function.py
marcel/function_args_parser.py
marcel/functionwrapper.py
marcel/helpformatter.py
marcel/job.py
marcel/job_mp.py
marcel/job_thread.py
marcel/jsonutil.py
marcel/locations.py
marcel/main.py
marcel/multilinereader.py
marcel/namespace.py
marcel/nestednamespace.py
marcel/opmodule.py
marcel/parse.py
marcel/parseargs.py
marcel/parser.py
marcel/picklefile.py
marcel/pickler.py
marcel/pipeline.py
marcel/plat.py
marcel/platform.py
marcel/reader.py
marcel/reduction.py
marcel/reservoir.py
marcel/runeditor.py
marcel/stringliteral.py
marcel/structish.py
marcel/tabcompleter.py
marcel/util.py
marcel/version.py
marcel/doc/__init__.py
marcel/doc/help_builtin.py
marcel/doc/help_color.py
marcel/doc/help_command.py
marcel/doc/help_configuration.py
marcel/doc/help_file.py
marcel/doc/help_function.py
marcel/doc/help_history_record.py
marcel/doc/help_interaction.py
marcel/doc/help_marcel.py
marcel/doc/help_namespace.py
marcel/doc/help_object.py
marcel/doc/help_operator.py
marcel/doc/help_overview.py
marcel/doc/help_pipeline.py
marcel/doc/help_process.py
marcel/doc/help_prompt.py
marcel/doc/help_startup.py
marcel/migration/__init__.py
marcel/migration/migration.py
marcel/migration/migration024.py
marcel/object/__init__.py
marcel/object/cluster.py
marcel/object/color.py
marcel/object/db.py
marcel/object/error.py
marcel/object/file.py
marcel/object/historyrecord.py
marcel/object/host.py
marcel/object/process.py
marcel/object/remote.py
marcel/object/renderable.py
marcel/object/workspace.py
marcel/op/__init__.py
marcel/op/apiop.py
marcel/op/args.py
marcel/op/assign.py
marcel/op/asyncfork.py
marcel/op/bash.py
marcel/op/bg.py
marcel/op/case.py
marcel/op/cast.py
marcel/op/cd.py
marcel/op/delete.py
marcel-0.37.1.dist-info/COPYING
marcel-0.37.1.dist-info/LICENSE
marcel-0.37.1.dist-info/METADATA
marcel-0.37.1.dist-info/WHEEL
marcel-0.37.1.dist-info/top_level.txt
marcel-0.37.1.dist-info/RECORD
