Metadata-Version: 2.1
Name: marcel
Version: 0.37.1
Summary: A modern shell
Home-page: https://www.marceltheshell.org
Author: Jack Orenstein
Author-email: jao@geophile.com
License: UNKNOWN
Platform: UNKNOWN
Classifier: Programming Language :: Python :: 3
Classifier: License :: OSI Approved :: GNU General Public License v3 (GPLv3)
Classifier: Operating System :: POSIX :: Linux
Requires-Python: >=3.9
License-File: LICENSE
License-File: COPYING
Requires-Dist: dill
Requires-Dist: prompt-toolkit
Requires-Dist: psutil
